normalisasitext/__init__.py
normalisasitext/preprocessing.py
normalization_text-1.0.0.dist-info/LICENSE.txt
normalization_text-1.0.0.dist-info/METADATA
normalization_text-1.0.0.dist-info/WHEEL
normalization_text-1.0.0.dist-info/top_level.txt
normalization_text-1.0.0.dist-info/RECORD
