Metadata-Version: 2.1
Name: normalization-text
Version: 1.0.0
Summary: Menormalisasikan Data Text
Author: Annisa Nuraini
Author-email: annisanuraini44@gmail.com
Classifier: License :: OSI Approved :: MIT License
Classifier: Programming Language :: Python :: 3
Classifier: Programming Language :: Python :: 3.7
Classifier: Programming Language :: Python :: 3.8
Classifier: Programming Language :: Python :: 3.9
Classifier: Programming Language :: Python :: 3.10
Classifier: Programming Language :: Python :: 3.11
License-File: LICENSE.txt
Requires-Dist: pandas
Requires-Dist: numpy
Requires-Dist: re
Requires-Dist: nltk
Requires-Dist: stopwords
Requires-Dist: nltk.corpus
